sepulsa/__init__.py
sepulsa/exceptions.py
sepulsa/provider.py
sepulsa/request.py
sepulsa/response.py
sepulsa/serializers.py
sepulsa/urls.py
sepulsa/core/__init__.py
sepulsa/core/exceptions.py
sepulsa/core/provider.py
sepulsa/core/remote_call.py
sepulsa/core/request.py
sepulsa/core/response.py
test/core/__init__.py
test/core/test_provider.py
test/core/test_remote_call.py
test/core/test_request.py
test/core/test_response.py
sepulsa-0.1.1.dist-info/LICENSE.md
sepulsa-0.1.1.dist-info/METADATA
sepulsa-0.1.1.dist-info/WHEEL
sepulsa-0.1.1.dist-info/top_level.txt
sepulsa-0.1.1.dist-info/RECORD
