Metadata-Version: 2.1
Name: sepulsa
Version: 0.1.1
Summary: Unofficial Sepulsa library for Python
Home-page: https://github.com/vousmeevoyez/sepulsa
Author: Kelvin Desman
Author-email: kelvindsmn@gmail.com
License: UNKNOWN
Platform: UNKNOWN
Classifier: Programming Language :: Python :: 3
Classifier: License :: OSI Approved :: MIT License
Classifier: Operating System :: OS Independent
Requires-Python: >=3.6
Requires-Dist: requests
